dbhelpy/__init__.py
dbhelpy/__main__.py
dbhelpy/dbhelpy.py
dbhelpy-0.6.0.dist-info/LICENSE
dbhelpy-0.6.0.dist-info/METADATA
dbhelpy-0.6.0.dist-info/WHEEL
dbhelpy-0.6.0.dist-info/top_level.txt
dbhelpy-0.6.0.dist-info/RECORD
